app/__init__.py
app/electric_meter.py
app/energy_meter.py
app/gas_meter.py
app/gauge_definitions.py
app/octopus_api_connection.py
app/octopus_usage_exporter.py
app/utils.py
octopus_usage_exporter-0.1.5.dist-info/licenses/LICENSE
octopus_usage_exporter-0.1.5.dist-info/METADATA
octopus_usage_exporter-0.1.5.dist-info/WHEEL
octopus_usage_exporter-0.1.5.dist-info/entry_points.txt
octopus_usage_exporter-0.1.5.dist-info/top_level.txt
octopus_usage_exporter-0.1.5.dist-info/RECORD
