Metadata-Version: 2.4
Name: octopus-usage-exporter
Version: 0.1.5
Summary: Prometheus exporter for Octopus Energy metrics. Works best when coupled with an Octopus Home Mini.
Author-email: Joseph Ryan-Palmer <joseph@ryan-palmer.com>
License-Expression: AGPL-3.0-or-later
Project-URL: Repository, https://github.com/josephrpalmer/octopus-usage-exporter.git
Project-URL: Issues, https://github.com/josephrpalmer/octopus-usage-exporter/issues
Requires-Python: >=3.13
License-File: LICENSE
Requires-Dist: backoff>=2.2.1
Requires-Dist: gql==3.4.1
Requires-Dist: prometheus-client==0.22.1
Requires-Dist: pydantic>=2.11.7
Requires-Dist: pydantic-settings>=2.10.1
Requires-Dist: python-jose==3.4.0
Requires-Dist: requests==2.32.4
Requires-Dist: requests-toolbelt==1.0.0
Dynamic: license-file
